neural_lib/__init__.py
neural_lib/dataset.py
neural_lib/model.py
neural_lib/neuannotation.py
neural_lib/neuenv.py
neural_lib/neujson.py
neural_lib/neutable.py
neural_lib/neutils.py
neural_lib/test_dataset.py
neural_lib/test_dataset_detection.py
neural_lib/torch_helper.py
neural_lib-23.1.20.dist-info/METADATA
neural_lib-23.1.20.dist-info/WHEEL
neural_lib-23.1.20.dist-info/top_level.txt
neural_lib-23.1.20.dist-info/RECORD
