Metadata-Version: 2.1
Name: neural-lib
Version: 23.1.20
Summary: neural lib test
Home-page: https://github.com/Neuralworks-io
Author: UNKNOWN
Author-email: UNKNOWN
License: UNKNOWN
Download-URL: https://github.com/Neuralworks-io/archive/0.0.tar.gz
Platform: UNKNOWN
